{"cameraMode":{"drawMode":0,"name":"Shaded","section":"Shading Mode"},"sceneLighting":true,"audioPlay":false,"sceneViewState":{"m_AlwaysRefresh":false,"showFog":true,"showSkybox":true,"showFlares":true,"showImageEffects":true,"showParticleSystems":true,"showVisualEffectGraphs":true,"m_FxEnabled":true},"in2DMode":false,"pivot":{"x":-146.71499633789063,"y":17.182477951049806,"z":-218.00230407714845},"rotation":{"x":-0.01697937585413456,"y":-0.9676386713981628,"z":-0.06650988012552262,"w":0.2431371957063675},"size":26.923240661621095,"orthographic":false}